<?xml version="1.0" encoding="utf-8" ?>
<dwsync>
<file name="1.jpg" server="ftp.netlesh.net//www/" local="128650135135156250" remote="128650584000000000" />
<file name="10.jpg" server="ftp.netlesh.net//www/" local="128650135154531250" remote="128650584000000000" />
<file name="11.jpg" server="ftp.netlesh.net//www/" local="128650135157500000" remote="128650584000000000" />
<file name="12.jpg" server="ftp.netlesh.net//www/" local="128650135160156250" remote="128650584600000000" />
<file name="2.jpg" server="ftp.netlesh.net//www/" local="128650135137187500" remote="128650584600000000" />
<file name="3.jpg" server="ftp.netlesh.net//www/" local="128650135138750000" remote="128650584600000000" />
<file name="4.jpg" server="ftp.netlesh.net//www/" local="128650135140312500" remote="128650584600000000" />
<file name="5.jpg" server="ftp.netlesh.net//www/" local="128650135142031250" remote="128650584600000000" />
<file name="6.jpg" server="ftp.netlesh.net//www/" local="128650135143593750" remote="128650584600000000" />
<file name="7.jpg" server="ftp.netlesh.net//www/" local="128650135145468750" remote="128650584600000000" />
<file name="8.jpg" server="ftp.netlesh.net//www/" local="128650135147187500" remote="128650584600000000" />
<file name="9.jpg" server="ftp.netlesh.net//www/" local="128650135151093750" remote="128650584600000000" />
</dwsync>